Metadata-Version: 2.1
Name: tabulationhashing
Version: 1.0.2
Summary: Implementation of Tabulation Hashing
Author-email: Martin Di Paola <use-github-issues@example.com>
License:                     GNU GENERAL PUBLIC LICENSE
Classifier: Programming Language :: Python :: 3
License-File: LICENSE
